[
	{
		"abbreviation": "Neuroscience (BS)",
		"catalog_uri": "https://catalog.utdallas.edu/2020/undergraduate/programs/bbs/neuroscience",
		"minimum_credit_hours": 120,
		"name": "Bachelor of Science in Neuroscience",
		"school": "School of Behavioral and Brain Sciences",
		"subtype": "Major",
		"year": "2020-2021"
	},
	"COMM 1311",
	"COMM 1315",
	"RHET 1302",
	"MATH 2414",
	"MATH 2417",
	["core","030",6],
	["core","040",3],
	["core","050",3],
	["core","060",6],
	["core","070",6],
	"PSY 2301",
	"PSY 2317",
	"STAT 1342",
	"STAT 2332",
	"CHEM 1312",
	"BIOL 2111",
	"BIOL 2281",
	"BIOL 2311",
	"CHEM 1111",
	"CHEM 1311",
	"CHEM 1112",
	"CHEM 1312",
	"MATH 2414",
	"MATH 2417",
	"PSY 2301",
	"PSY 2317",
	"STAT 1342",
	"STAT 2332",
	"NSC 3361",
	"NSC 4352",
	"NSC 4353",
	"NSC 4354",
	"NSC 4356",
	"NSC 4363",
	"NSC 4366",
	"NSC 4350",
	"NSC 4351",
	"NSC 4358",
	"NSC 4362",
	"NSC 4364",
	"NSC 4382",
	"NSC 4372",
	"NSC 4378",
	"NSC 4387",
	"NSC 4388",
	"NSC 4397",
	"NSC 4V75",
	"NSC 4V98",
	"NSC 4V99",
	"BIOL 2112",
	"BIOL 2312",
	"BIOL 3161",
	"BIOL 3361",
	"CHEM 2123",
	"CHEM 2125",
	"CHEM 2323",
	"CHEM 2325",
	"PHYS 1301",
	"PHYS 2125",
	"NSC 4355",
	"NSC 4357",
	"NSC 4358",
	"NSC 4359",
	"NSC 4362",
	"NSC 4367",
	"NSC 4382",
	"NSC 4371",
	"NSC 4372",
	"NSC 4374",
	"NSC 4376",
	"NSC 4391",
	"NSC 4397",
	"NSC 4V75",
	"NSC 4V98",
	"NSC 4V99",
	"BIOL 2112",
	"BIOL 2312",
	"BIOL 3161",
	"BIOL 3361",
	"CHEM 2123",
	"CHEM 2125",
	"CHEM 2323",
	"CHEM 2325",
	"PHYS 1301",
	"PHYS 2125",
	"NSC 4360",
	"NSC 4361",
	"NSC 4193",
	"NSC 4391",
	"NSC 4394",
	"NSC 4395",
	"NSC 4397",
	"NSC 4395",
	"NSC 4V99",
	"ENTP 3301",
	"ENTP 4311",
	"HMGT 3301",
	"HMGT 3310",
	"MKT 3300",
	"MKT 3330",
	"NSC 3361",
	"NSC 4352",
	"NSC 4354",
	"NSC 4356",
	"NSC 4363",
	"NSC 4366",
	"NSC 4350",
	"NSC 4351",
	"NSC 4358",
	"NSC 4362",
	"NSC 4364",
	"NSC 4372",
	"NSC 4378",
	"NSC 4353",
	"NSC 4357",
	"NSC 4358",
	"NSC 4362",
	"NSC 4367",
	"NSC 4371",
	"NSC 4372",
	"NSC 4376",
	"NSC 4360",
	"NSC 4361",
	"NSC 4391",
	"NSC 4193",
	"NSC 4394",
	"NSC 4395",
	"NSC 4397",
	"NSC 4V99"
]